<?xml version="1.0" encoding="ISO-8859-1" ?>
<scores>
    <party playerName="b4n92uid" levelName="Desert" timestamp="1277303114" playTime="60" playMod="0" score="127" />
    <party playerName="b4n92uid" levelName="Desert" timestamp="1277305561" playTime="60" playMod="0" score="122" />
    <party playerName="b4n92uid" levelName="Desert" timestamp="1277379650" playTime="60" playMod="0" score="149" />
    <party playerName="b4n92uid" levelName="Desert" timestamp="1277379731" playTime="60" playMod="2" score="176" />
    <party playerName="b4n92uid" levelName="Desert" timestamp="1277379805" playTime="60" playMod="1" score="75" />
    <party playerName="b4n92uid" levelName="Desert" timestamp="1277399070" playTime="60" playMod="0" score="134" />
    <party playerName="b4n92uid" levelName="Desert" timestamp="1277754568" playTime="60" playMod="0" score="85" />
    <party playerName="b4n92uid" levelName="Desert" timestamp="1277759399" playTime="0" playMod="2" score="11" />
    <party playerName="b4n92uid" levelName="Desert" timestamp="1277928794" playTime="60" playMod="0" score="100" />
    <party playerName="b4n92uid" levelName="StarField" timestamp="1278100018" playTime="0" playMod="2" score="0" />
    <party playerName="b4n92uid" levelName="StarField" timestamp="1278104235" playTime="60" playMod="0" score="5" />
    <party playerName="b4n92uid" levelName="StarField" timestamp="1278194791" playTime="60" playMod="0" score="38" />
    <party playerName="b4n92uid" levelName="StarField" timestamp="1278195128" playTime="60" playMod="0" score="74" />
    <party playerName="b4n92uid" levelName="StarField" timestamp="1278201022" playTime="60" playMod="0" score="67" />
    <party playerName="b4n92uid" levelName="StarField" timestamp="1278547773" playTime="60" playMod="0" score="100" />
    <party playerName="b4n92uid" levelName="JumpMe" timestamp="1278723010" playTime="60" playMod="0" score="28" />
    <party playerName="b4n92uid" levelName="JumpMe" timestamp="1278767253" playTime="60" playMod="0" score="205" />
    <party playerName="b4n92uid" levelName="Travell" timestamp="1278785997" playTime="60" playMod="0" score="31" />
    <party playerName="b4n92uid" levelName="JumpMe" timestamp="1278792706" playTime="60" playMod="0" score="103" />
    <party playerName="b4n92uid" levelName="Travell" timestamp="1278941040" playTime="60" playMod="0" score="47" />
    <party playerName="b4n92uid" levelName="StarField" timestamp="1278947608" playTime="300" playMod="0" score="400" />
    <party playerName="b4n92uid" levelName="StarField" timestamp="1278954000" playTime="60" playMod="0" score="73" />
    <party playerName="b4n92uid" levelName="StarField" timestamp="1278955223" playTime="60" playMod="2" score="66" />
    <party playerName="b4n92uid" levelName="StarField" timestamp="1278955250" playTime="60" playMod="2" score="77" />
    <party playerName="b4n92uid" levelName="Travell" timestamp="1278968372" playTime="60" playMod="2" score="33" />
    <party playerName="b4n92uid" levelName="StarField" timestamp="1278969297" playTime="60" playMod="0" score="0" />
    <party playerName="b4n92uid" levelName="StarField" timestamp="1278969558" playTime="60" playMod="0" score="0" />
    <party playerName="b4n92uid" levelName="StarField" timestamp="1279041700" playTime="60" playMod="2" score="0" />
    <party playerName="b4n92uid" playerModel="data/players/thecube.bpd" levelPath="data/levels/starfield.bld" levelName="StarField" playMod="0" playersCount="4" playTime="300" timestamp="1279055041" score="509" />
    <party playerName="b4n92uid" playerModel="data/players/thecube.bpd" levelPath="data/levels/travell.bld" levelName="Travell" playMod="0" playersCount="4" playTime="300" timestamp="1279055356" score="525" />
    <party playerName="b4n92uid" playerModel="data/players/thecube.bpd" levelPath="data/levels/desert.bld" levelName="Desert" playMod="0" playersCount="4" playTime="300" timestamp="1279055672" score="481" />
    <party playerName="b4n92uid" playerModel="data/players/thecube.bpd" levelPath="data/levels/jumpme.bld" levelName="JumpMe" playMod="2" playersCount="4" playTime="300" timestamp="1279103576" score="33" />
</scores>
